playwright_mcp/__init__.py
playwright_mcp/server.py
mseep_playwright_mcp-0.1.2.dist-info/METADATA
mseep_playwright_mcp-0.1.2.dist-info/WHEEL
mseep_playwright_mcp-0.1.2.dist-info/entry_points.txt
mseep_playwright_mcp-0.1.2.dist-info/top_level.txt
mseep_playwright_mcp-0.1.2.dist-info/RECORD
