Metadata-Version: 2.4
Name: mseep-playwright-mcp
Version: 0.1.2
Summary: Playwright wrapper for MCP
Author-email: mseep <support@skydeck.ai>
Requires-Python: >=3.11
Requires-Dist: mcp>=1.3.0
Requires-Dist: playwright>=1.50.0
